ZlBusApi/ZlBusApi.py
ZlBusApi/ZlBusApiExample.py
ZlBusApi/__init__.py
ZlBusApi/bin/linux/libzlbus_arm64.so
ZlBusApi/bin/linux/libzlbus_x64.so
ZlBusApi/bin/win/zlbus_x64.dll
ZlBusApi/zlbusModules/__init__.py
ZlBusApi/zlbusModules/zlbusApiType.py
ZlBusApi/zlbusModules/zlbusApi_eBlockId.py
ZlBusApi/zlbusModules/zlbusBaseType.py
ZlBusApi/zlbusModules/zlbusConfig.py
ZlBusApi/zlbusModules/zlbusError.py
ZlBusApi/zlbusModules/zlbusStackConfig.py
zlbusapi-0.5.7.dist-info/METADATA
zlbusapi-0.5.7.dist-info/WHEEL
zlbusapi-0.5.7.dist-info/top_level.txt
zlbusapi-0.5.7.dist-info/RECORD
