Metadata-Version: 2.1
Name: zlbusapi
Version: 0.5.7
Summary: ZeroLab Bus API for Python
Author: ZeroLab
Author-email: larry.lv@zero-lab.tech
Classifier: Programming Language :: Python :: 3
Classifier: License :: OSI Approved :: MIT License
Classifier: Operating System :: OS Independent
Requires-Python: >=3.8
